flask_redis/__init__.py
flask_redis/__version__.py
flask_redis/cluster.py
flask_redis/ext.py
flask_redis/macro.py
flask_redis/redis.py
flask_redis/sentinel.py
flask_redis_ext-1.0.0.dist-info/LICENSE
flask_redis_ext-1.0.0.dist-info/METADATA
flask_redis_ext-1.0.0.dist-info/WHEEL
flask_redis_ext-1.0.0.dist-info/top_level.txt
flask_redis_ext-1.0.0.dist-info/RECORD
